acrclient/__init__.py
acrclient/client.py
acrclient/models.py
acrclient/py.typed
acrclient-0.5.2.dist-info/METADATA
acrclient-0.5.2.dist-info/WHEEL
acrclient-0.5.2.dist-info/RECORD
